simple_versioner.py
simple_versioner-0.3.0.dist-info/DESCRIPTION.rst
simple_versioner-0.3.0.dist-info/METADATA
simple_versioner-0.3.0.dist-info/RECORD
simple_versioner-0.3.0.dist-info/WHEEL
simple_versioner-0.3.0.dist-info/metadata.json
simple_versioner-0.3.0.dist-info/top_level.txt
