Metadata-Version: 2.0
Name: simple-versioner
Version: 0.3.0
Summary: Simple versioning module for python packages.
Home-page: https://github.com/cournape/simple-versioner
Author: David Cournapeau
Author-email: cournape@gmail.com
License: MIT
Platform: UNKNOWN
